qeclab/__init__.py
qeclab-0.3.1.dist-info/WHEEL
qeclab-0.3.1.dist-info/METADATA
qeclab-0.3.1.dist-info/RECORD
