Metadata-Version: 2.1
Name: qeclab
Version: 0.3.1
Summary: 
Author: maxtremblay
Author-email: m@xtremblay.ca
Requires-Python: >=3.8,<3.10
Classifier: Programming Language :: Python :: 3
Classifier: Programming Language :: Python :: 3.8
Classifier: Programming Language :: Python :: 3.9
Requires-Dist: dill (>=0.3.4,<0.4.0)
Requires-Dist: multiprocess (>=0.70.12,<0.71.0)
Requires-Dist: pandas (>=1.3.0,<2.0.0)
Requires-Dist: qecstruct (>=0.2.6,<0.3.0)
